tig3r
