Metadata-Version: 2.1
Name: tig3r
Version: 0.3
Summary: Useful library in many jobs
Author: tiger
Author-email: tigercod3r@gmail.com
Classifier: Programming Language :: Python :: 3
Classifier: License :: OSI Approved :: MIT License
Classifier: Operating System :: OS Independent
License-File: LICENSE
